racelab/__init__.py
racelab/load.py
racelab/optimize.py
racelab/plot.py
racelab/deepracer/__init__.py
racelab/deepracer/track.py
racelab/deepracer/data/2022_april_open.npy
racelab/deepracer/data/2022_april_open_ccw.npy
racelab/deepracer/data/2022_april_open_cw.npy
racelab/deepracer/data/2022_april_pro.npy
racelab/deepracer/data/2022_april_pro_ccw.npy
racelab/deepracer/data/2022_april_pro_cw.npy
racelab/deepracer/data/2022_august_open.npy
racelab/deepracer/data/2022_august_open_ccw.npy
racelab/deepracer/data/2022_august_open_cw.npy
racelab/deepracer/data/2022_august_pro.npy
racelab/deepracer/data/2022_august_pro_ccw.npy
racelab/deepracer/data/2022_august_pro_cw.npy
racelab/deepracer/data/2022_july_open.npy
racelab/deepracer/data/2022_july_pro.npy
racelab/deepracer/data/2022_july_pro_ccw.npy
racelab/deepracer/data/2022_july_pro_cw.npy
racelab/deepracer/data/2022_june_open.npy
racelab/deepracer/data/2022_june_open_ccw.npy
racelab/deepracer/data/2022_june_open_cw.npy
racelab/deepracer/data/2022_june_pro.npy
racelab/deepracer/data/2022_june_pro_ccw.npy
racelab/deepracer/data/2022_june_pro_cw.npy
racelab/deepracer/data/2022_march_open.npy
racelab/deepracer/data/2022_march_open_ccw.npy
racelab/deepracer/data/2022_march_open_cw.npy
racelab/deepracer/data/2022_march_pro.npy
racelab/deepracer/data/2022_march_pro_ccw.npy
racelab/deepracer/data/2022_march_pro_cw.npy
racelab/deepracer/data/2022_may_open.npy
racelab/deepracer/data/2022_may_open_ccw.npy
racelab/deepracer/data/2022_may_open_cw.npy
racelab/deepracer/data/2022_may_pro.npy
racelab/deepracer/data/2022_may_pro_ccw.npy
racelab/deepracer/data/2022_may_pro_cw.npy
racelab/deepracer/data/2022_october_open.npy
racelab/deepracer/data/2022_october_open_ccw.npy
racelab/deepracer/data/2022_october_open_cw.npy
racelab/deepracer/data/2022_october_pro.npy
racelab/deepracer/data/2022_october_pro_ccw.npy
racelab/deepracer/data/2022_october_pro_cw.npy
racelab/deepracer/data/2022_reinvent_champ.npy
racelab-0.0.6.dist-info/LICENSE
racelab-0.0.6.dist-info/METADATA
racelab-0.0.6.dist-info/WHEEL
racelab-0.0.6.dist-info/top_level.txt
racelab-0.0.6.dist-info/RECORD
