Metadata-Version: 2.1
Name: racelab
Version: 0.0.6
Summary: A Framework for Car Racing
Author-email: Li Yuan <lyuan@gd.edu.kg>, Hengyuan Liu <hliu@gd.edu.kg>
Maintainer-email: Li Yuan <lyuan@gd.edu.kg>, Hengyuan Liu <hliu@gd.edu.kg>
Project-URL: Homepage, https://github.com/GitData-GA/racelab/
Project-URL: Issues, https://github.com/GitData-GA/racelab/issues
Classifier: Programming Language :: Python :: 3
Classifier: License :: OSI Approved :: MIT License
Classifier: Operating System :: OS Independent
Requires-Python: >=3.8
License-File: LICENSE
